PyTektronixScope/DPO3000.py
PyTektronixScope/IviScope.py
PyTektronixScope/PyTektronixInputType.py
PyTektronixScope/PyTektronixScope.py
PyTektronixScope/PyTektronixScopeBis.py
PyTektronixScope/VISA_wrapper.py
PyTektronixScope/VISA_wrapper_metaclass.py
PyTektronixScope/__init__.py
PyTektronixScope-0.3.1.dist-info/METADATA
PyTektronixScope-0.3.1.dist-info/WHEEL
PyTektronixScope-0.3.1.dist-info/top_level.txt
PyTektronixScope-0.3.1.dist-info/RECORD
