Metadata-Version: 2.1
Name: PyTektronixScope
Version: 0.3.1
Summary: Interface to Tektronix Scope
Home-page: https://github.com/clade/PyTektronixScope
Author: Pierre Cladé
Author-email: pierre.clade@spectro.jussieu.fr
Maintainer: Pierre Cladé
Maintainer-email: pierre.clade@spectro.jussieu.fr
License: This software can be used under one of the following two licenses: (1) The BSD license. (2) Any other license, as long as it is obtained from the original author.
Keywords: Tektronix,scope,Data Acquisition
Classifier: Development Status :: 4 - Beta
Classifier: Intended Audience :: Developers
Classifier: Intended Audience :: Education
Classifier: Intended Audience :: Other Audience
Classifier: Intended Audience :: Science/Research
Classifier: License :: OSI Approved :: BSD License
Classifier: Programming Language :: Python
Classifier: Topic :: Scientific/Engineering
Classifier: Topic :: Scientific/Engineering :: Physics
Classifier: Topic :: Software Development
Classifier: Topic :: Software Development :: Libraries
Classifier: Topic :: Software Development :: Libraries :: Python Modules
Requires: pyvisa
